merak/__init__.py
merak/datalib.py
merak/main.py
merak/commands/__init__.py
merak/commands/base.py
merak/commands/cythonize.py
merak/core/__init__.py
merak/core/base.py
merak/core/cybuild.py
merak/core/errors.py
merak/core/refactor/__init__.py
merak/core/refactor/ast_.py
merak/core/refactor/restructure.py
merak/core/refactor/rewrite.py
merak/core/refactor/transform.py
merak/data/__init__.tmpl
merak/data/setup.tmpl
merak/utils/__init__.py
merak/utils/misc.py
merak/utils/subproc.py
merak-0.3.5.dist-info/LICENSE
merak-0.3.5.dist-info/METADATA
merak-0.3.5.dist-info/WHEEL
merak-0.3.5.dist-info/entry_points.txt
merak-0.3.5.dist-info/top_level.txt
merak-0.3.5.dist-info/RECORD
