Metadata-Version: 2.1
Name: merak
Version: 0.3.5
Summary: Python binary package builder (via Cython)
Author-email: "(David) Siu-Kei Muk" <david.muk@proton.me>
License: Copyright 2021 (David) Siu-Kei Muk. All Rights Reserved.
Project-URL: Repository, https://github.com/dave-msk/merak
Keywords: merak,cython,binary,package,build
Classifier: Development Status :: 4 - Beta
Classifier: Intended Audience :: Developers
Classifier: License :: OSI Approved :: Apache Software License
Classifier: Operating System :: OS Independent
Classifier: Programming Language :: Cython
Classifier: Programming Language :: Python
Classifier: Programming Language :: Python :: 3.8
Classifier: Programming Language :: Python :: 3.9
Classifier: Programming Language :: Python :: 3.10
Classifier: Programming Language :: Python :: 3.11
Classifier: Programming Language :: Python :: 3.12
Classifier: Topic :: Software Development
Classifier: Topic :: Software Development :: Build Tools
Classifier: Topic :: Software Development :: Compilers
Requires-Python: >=3.8
License-File: LICENSE
Requires-Dist: cement <4.0.0,>=3.0.4
Requires-Dist: colorlog >=4.6.2
Requires-Dist: cython >=3.0.0
Requires-Dist: setuptools >=72.1.0
